.coveragerc
.gitignore
CMakeLists.txt
LICENSE
MANIFEST.in
README.md
readthedocs.yml
setup.cfg
setup.py
.github/workflows/building-conda.yml
.github/workflows/building.yml
.github/workflows/linting.yml
.github/workflows/stale.yml
.github/workflows/testing.yml
.github/workflows/cuda/cu101-Linux-env.sh
.github/workflows/cuda/cu101-Linux.sh
.github/workflows/cuda/cu101-Windows-env.sh
.github/workflows/cuda/cu101-Windows.sh
.github/workflows/cuda/cu102-Linux-env.sh
.github/workflows/cuda/cu102-Linux.sh
.github/workflows/cuda/cu102-Windows-env.sh
.github/workflows/cuda/cu102-Windows.sh
.github/workflows/cuda/cu111-Linux-env.sh
.github/workflows/cuda/cu111-Linux.sh
.github/workflows/cuda/cu111-Windows-env.sh
.github/workflows/cuda/cu111-Windows.sh
.github/workflows/cuda/cu113-Linux-env.sh
.github/workflows/cuda/cu113-Linux.sh
.github/workflows/cuda/cu113-Windows-env.sh
.github/workflows/cuda/cu113-Windows.sh
.github/workflows/cuda/cu115-Linux-env.sh
.github/workflows/cuda/cu115-Linux.sh
.github/workflows/cuda/cu115-Windows-env.sh
.github/workflows/cuda/cu115-Windows.sh
.github/workflows/cuda/cu116-Linux-env.sh
.github/workflows/cuda/cu116-Linux.sh
.github/workflows/cuda/cu116-Windows-env.sh
.github/workflows/cuda/cu116-Windows.sh
.github/workflows/cuda/cu117-Linux-env.sh
.github/workflows/cuda/cu117-Linux.sh
.github/workflows/cuda/cu117-Windows-env.sh
.github/workflows/cuda/cu117-Windows.sh
.github/workflows/cuda/cu118-Linux-env.sh
.github/workflows/cuda/cu118-Linux.sh
.github/workflows/cuda/cu118-Windows-env.sh
.github/workflows/cuda/cu118-Windows.sh
.github/workflows/cuda/cu121-Linux-env.sh
.github/workflows/cuda/cu121-Linux.sh
.github/workflows/cuda/cu121-Windows-env.sh
.github/workflows/cuda/cu121-Windows.sh
benchmark/.gitignore
benchmark/gather.py
benchmark/scatter_segment.py
cmake/TorchScatterConfig.cmake.in
conda/pytorch-scatter/README.md
conda/pytorch-scatter/build_conda.sh
conda/pytorch-scatter/meta.yaml
csrc/extensions.h
csrc/macros.h
csrc/scatter.cpp
torch_scatter.egg-info/PKG-INFO
torch_scatter.egg-info/SOURCES.txt
torch_scatter.egg-info/dependency_links.txt
torch_scatter.egg-info/requires.txt
torch_scatter.egg-info/top_level.txt
