Metadata-Version: 2.1
Name: torch-scatter
Version: 2.1.2
Summary: PyTorch Extension Library of Optimized Scatter Operations
Home-page: https://github.com/rusty1s/pytorch_scatter
Download-URL: https://github.com/rusty1s/pytorch_scatter/archive/2.1.2.tar.gz
Author: Matthias Fey
Author-email: matthias.fey@tu-dortmund.de
License: UNKNOWN
Keywords: pytorch,scatter,segment,gather
Platform: UNKNOWN
Classifier: Development Status :: 5 - Production/Stable
Classifier: License :: OSI Approved :: MIT License
Classifier: Programming Language :: Python
Classifier: Programming Language :: Python :: 3.8
Classifier: Programming Language :: Python :: 3.9
Classifier: Programming Language :: Python :: 3.10
Classifier: Programming Language :: Python :: 3.11
Classifier: Programming Language :: Python :: 3 :: Only
Requires-Python: >=3.8
Provides-Extra: test
License-File: LICENSE
